{
    "stories": [
        {
            "id": 1,
            "user_id": 1,
            "images": [
                {
                    "id": 100,
                    "url": "https://www.dummyimage.com/400x600/30b2cf/cfd0e6&text=This+image+is+from+dummyimage.com"
                    "posted_at": "2025-03-06T08:00:00Z",
                    "seen": false,
                    "liked": false
                },
                {
                    "id": 102,
                    "url": "https://www.dummyimage.com/400x600/9332cf/cfd0e6&text=This+image+is+from+dummyimage.com"
                    "posted_at": "2025-03-06T08:00:00Z",
                    "seen": false,
                    "liked": false
                },
                {
                    "id": 103,
                    "url": "https://www.dummyimage.com/400x600/34cf3e/cfd0e6&text=This+image+is+from+dummyimage.com"
                    "posted_at": "2025-03-06T08:00:00Z",
                    "seen": false,
                    "liked": false
                }
            ]
        },
        {
            "id": 2,
            "user_id": 2,
            "images": [
                {
                    "id": 200,
                    "url": "https://www.dummyimage.com/400x600/30b2cf/cfd0e6&text=This+image+is+from+dummyimage.com"
                    "posted_at": "2025-03-06T08:00:00Z",
                    "seen": false,
                    "liked": false
                },
                {
                    "id": 202,
                    "url": "https://www.dummyimage.com/400x600/9332cf/cfd0e6&text=This+image+is+from+dummyimage.com"
                    "posted_at": "2025-03-06T08:00:00Z",
                    "seen": false,
                    "liked": false
                },
                {
                    "id": 203,
                    "url": "https://www.dummyimage.com/400x600/34cf3e/cfd0e6&text=This+image+is+from+dummyimage.com"
                    "posted_at": "2025-03-06T08:00:00Z",
                    "seen": false,
                    "liked": false
                }
            ]
        },
        {
            "id": 3,
            "user_id": 3,
            "images": [
                {
                    "id": 300,
                    "url": "https://www.dummyimage.com/400x600/30b2cf/cfd0e6&text=This+image+is+from+dummyimage.com"
                    "posted_at": "2025-03-06T08:00:00Z",
                    "seen": false,
                    "liked": false
                },
                {
                    "id": 302,
                    "url": "https://www.dummyimage.com/400x600/30b2cf/cfd0e6&text=This+image+is+from+dummyimage.com"
                    "posted_at": "2025-03-06T08:00:00Z",
                    "seen": false,
                    "liked": false
                },
                {
                    "id": 303,
                    "url": "https://www.dummyimage.com/400x600/30b2cf/cfd0e6&text=This+image+is+from+dummyimage.com"
                    "posted_at": "2025-03-06T08:00:00Z",
                    "seen": false,
                    "liked": false
                }
            ]
        },
        {
            "id": 4,
            "user_id": 4,
            "images": [
                {
                    "id": 400,
                    "url": "https://www.dummyimage.com/400x600/30b2cf/cfd0e6&text=This+image+is+from+dummyimage.com"
                    "posted_at": "2025-03-06T08:00:00Z",
                    "seen": false,
                    "liked": false
                },
                {
                    "id": 402,
                    "url": "https://www.dummyimage.com/400x600/30b2cf/cfd0e6&text=This+image+is+from+dummyimage.com"
                    "posted_at": "2025-03-06T08:00:00Z",
                    "seen": false,
                    "liked": false
                },
                {
                    "id": 403,
                    "url": "https://www.dummyimage.com/400x600/30b2cf/cfd0e6&text=This+image+is+from+dummyimage.com"
                    "posted_at": "2025-03-06T08:00:00Z",
                    "seen": false,
                    "liked": false
                }
            ]
        },
        {
            "id": 5,
            "user_id": 5,
            "images": [
                {
                    "id": 500,
                    "url": "https://www.dummyimage.com/400x600/30b2cf/cfd0e6&text=This+image+is+from+dummyimage.com"
                    "posted_at": "2025-03-06T08:00:00Z",
                    "seen": false,
                    "liked": false
                },
                {
                    "id": 502,
                    "url": "https://www.dummyimage.com/400x600/30b2cf/cfd0e6&text=This+image+is+from+dummyimage.com"
                    "posted_at": "2025-03-06T08:00:00Z",
                    "seen": false,
                    "liked": false
                },
                {
                    "id": 503,
                    "url": "https://www.dummyimage.com/400x600/30b2cf/cfd0e6&text=This+image+is+from+dummyimage.com"
                    "posted_at": "2025-03-06T08:00:00Z",
                    "seen": false,
                    "liked": false
                }
            ]
        },
        {
            "id": 6,
            "user_id": 6,
            "images": [
                {
                    "id": 600,
                    "url": "https://www.dummyimage.com/400x600/30b2cf/cfd0e6&text=This+image+is+from+dummyimage.com"
                    "posted_at": "2025-03-06T08:00:00Z",
                    "seen": false,
                    "liked": false
                },
                {
                    "id": 602,
                    "url": "https://www.dummyimage.com/400x600/30b2cf/cfd0e6&text=This+image+is+from+dummyimage.com"
                    "posted_at": "2025-03-06T08:00:00Z",
                    "seen": false,
                    "liked": false
                },
                {
                    "id": 603,
                    "url": "https://www.dummyimage.com/400x600/30b2cf/cfd0e6&text=This+image+is+from+dummyimage.com"
                    "posted_at": "2025-03-06T08:00:00Z",
                    "seen": false,
                    "liked": false
                }
            ]
        },
        {
            "id": 7,
            "user_id": 7,
            "images": [
                {
                    "id": 700,
                    "url": "https://www.dummyimage.com/400x600/30b2cf/cfd0e6&text=This+image+is+from+dummyimage.com"
                    "posted_at": "2025-03-06T08:00:00Z",
                    "seen": false,
                    "liked": false
                },
                {
                    "id": 702,
                    "url": "https://www.dummyimage.com/400x600/30b2cf/cfd0e6&text=This+image+is+from+dummyimage.com"
                    "posted_at": "2025-03-06T08:00:00Z",
                    "seen": false,
                    "liked": false
                },
                {
                    "id": 703,
                    "url": "https://www.dummyimage.com/400x600/30b2cf/cfd0e6&text=This+image+is+from+dummyimage.com"
                    "posted_at": "2025-03-06T08:00:00Z",
                    "seen": false,
                    "liked": false
                }
            ]
        },
        {
            "id": 8,
            "user_id": 8,
            "images": [
                {
                    "id": 800,
                    "url": "https://www.dummyimage.com/400x600/30b2cf/cfd0e6&text=This+image+is+from+dummyimage.com"
                    "posted_at": "2025-03-06T08:00:00Z",
                    "seen": false,
                    "liked": false
                },
                {
                    "id": 802,
                    "url": "https://www.dummyimage.com/400x600/30b2cf/cfd0e6&text=This+image+is+from+dummyimage.com"
                    "posted_at": "2025-03-06T08:00:00Z",
                    "seen": false,
                    "liked": false
                },
                {
                    "id": 803,
                    "url": "https://www.dummyimage.com/400x600/30b2cf/cfd0e6&text=This+image+is+from+dummyimage.com"
                    "posted_at": "2025-03-06T08:00:00Z",
                    "seen": false,
                    "liked": false
                }
            ]
        },
        {
            "id": 9,
            "user_id": 9,
            "images": [
                {
                    "id": 900,
                    "url": "https://www.dummyimage.com/400x600/30b2cf/cfd0e6&text=This+image+is+from+dummyimage.com"
                    "posted_at": "2025-03-06T08:00:00Z",
                    "seen": false,
                    "liked": false
                },
                {
                    "id": 902,
                    "url": "https://www.dummyimage.com/400x600/30b2cf/cfd0e6&text=This+image+is+from+dummyimage.com"
                    "posted_at": "2025-03-06T08:00:00Z",
                    "seen": false,
                    "liked": false
                },
                {
                    "id": 903,
                    "url": "https://www.dummyimage.com/400x600/30b2cf/cfd0e6&text=This+image+is+from+dummyimage.com"
                    "posted_at": "2025-03-06T08:00:00Z",
                    "seen": false,
                    "liked": false
                }
            ]
        },
        {
            "id": 10,
            "user_id": 10,
            "images": [
                {
                    "id": 1000,
                    "url": "https://www.dummyimage.com/400x600/30b2cf/cfd0e6&text=This+image+is+from+dummyimage.com"
                    "posted_at": "2025-03-06T08:00:00Z",
                    "seen": false,
                    "liked": false
                },
                {
                    "id": 1002,
                    "url": "https://www.dummyimage.com/400x600/30b2cf/cfd0e6&text=This+image+is+from+dummyimage.com"
                    "posted_at": "2025-03-06T08:00:00Z",
                    "seen": false,
                    "liked": false
                },
                {
                    "id": 1003,
                    "url": "https://www.dummyimage.com/400x600/30b2cf/cfd0e6&text=This+image+is+from+dummyimage.com"
                    "posted_at": "2025-03-06T08:00:00Z",
                    "seen": false,
                    "liked": false
                }
            ]
        },
        {
            "id": 11,
            "user_id": 11,
            "images": [
                {
                    "id": 1100,
                    "url": "https://www.dummyimage.com/400x600/30b2cf/cfd0e6&text=This+image+is+from+dummyimage.com"
                    "posted_at": "2025-03-06T08:00:00Z",
                    "seen": false,
                    "liked": false
                },
                {
                    "id": 1102,
                    "url": "https://www.dummyimage.com/400x600/30b2cf/cfd0e6&text=This+image+is+from+dummyimage.com"
                    "posted_at": "2025-03-06T08:00:00Z",
                    "seen": false,
                    "liked": false
                },
                {
                    "id": 1103,
                    "url": "https://www.dummyimage.com/400x600/30b2cf/cfd0e6&text=This+image+is+from+dummyimage.com"
                    "posted_at": "2025-03-06T08:00:00Z",
                    "seen": false,
                    "liked": false
                }
            ]
        },
        {
            "id": 12,
            "user_id": 12,
            "images": [
                {
                    "id": 1200,
                    "url": "https://www.dummyimage.com/400x600/30b2cf/cfd0e6&text=This+image+is+from+dummyimage.com"
                    "posted_at": "2025-03-06T08:00:00Z",
                    "seen": false,
                    "liked": false
                },
                {
                    "id": 1202,
                    "url": "https://www.dummyimage.com/400x600/30b2cf/cfd0e6&text=This+image+is+from+dummyimage.com"
                    "posted_at": "2025-03-06T08:00:00Z",
                    "seen": false,
                    "liked": false
                },
                {
                    "id": 1203,
                    "url": "https://www.dummyimage.com/400x600/30b2cf/cfd0e6&text=This+image+is+from+dummyimage.com"
                    "posted_at": "2025-03-06T08:00:00Z",
                    "seen": false,
                    "liked": false
                }
            ]
        },
        {
            "id": 13,
            "user_id": 13,
            "images": [
                {
                    "id": 1300,
                    "url": "https://www.dummyimage.com/400x600/30b2cf/cfd0e6&text=This+image+is+from+dummyimage.com"
                    "posted_at": "2025-03-06T08:00:00Z",
                    "seen": false,
                    "liked": false
                },
                {
                    "id": 1302,
                    "url": "https://www.dummyimage.com/400x600/30b2cf/cfd0e6&text=This+image+is+from+dummyimage.com"
                    "posted_at": "2025-03-06T08:00:00Z",
                    "seen": false,
                    "liked": false
                },
                {
                    "id": 1303,
                    "url": "https://www.dummyimage.com/400x600/30b2cf/cfd0e6&text=This+image+is+from+dummyimage.com"
                    "posted_at": "2025-03-06T08:00:00Z",
                    "seen": false,
                    "liked": false
                }
            ]
        },
        {
            "id": 14,
            "user_id": 14,
            "images": [
                {
                    "id": 1400,
                    "url": "https://www.dummyimage.com/400x600/30b2cf/cfd0e6&text=This+image+is+from+dummyimage.com"
                    "posted_at": "2025-03-06T08:00:00Z",
                    "seen": false,
                    "liked": false
                },
                {
                    "id": 1402,
                    "url": "https://www.dummyimage.com/400x600/30b2cf/cfd0e6&text=This+image+is+from+dummyimage.com"
                    "posted_at": "2025-03-06T08:00:00Z",
                    "seen": false,
                    "liked": false
                },
                {
                    "id": 1403,
                    "url": "https://www.dummyimage.com/400x600/30b2cf/cfd0e6&text=This+image+is+from+dummyimage.com"
                    "posted_at": "2025-03-06T08:00:00Z",
                    "seen": false,
                    "liked": false
                }
            ]
        },
        {
            "id": 15,
            "user_id": 15,
            "images": [
                {
                    "id": 1500,
                    "url": "https://www.dummyimage.com/400x600/30b2cf/cfd0e6&text=This+image+is+from+dummyimage.com"
                    "posted_at": "2025-03-06T08:00:00Z",
                    "seen": false,
                    "liked": false
                },
                {
                    "id": 1502,
                    "url": "https://www.dummyimage.com/400x600/30b2cf/cfd0e6&text=This+image+is+from+dummyimage.com"
                    "posted_at": "2025-03-06T08:00:00Z",
                    "seen": false,
                    "liked": false
                },
                {
                    "id": 1503,
                    "url": "https://www.dummyimage.com/400x600/30b2cf/cfd0e6&text=This+image+is+from+dummyimage.com"
                    "posted_at": "2025-03-06T08:00:00Z",
                    "seen": false,
                    "liked": false
                }
            ]
        },
        {
            "id": 16,
            "user_id": 16,
            "images": [
                {
                    "id": 1600,
                    "url": "https://www.dummyimage.com/400x600/30b2cf/cfd0e6&text=This+image+is+from+dummyimage.com"
                    "posted_at": "2025-03-06T08:00:00Z",
                    "seen": false,
                    "liked": false
                },
                {
                    "id": 1602,
                    "url": "https://www.dummyimage.com/400x600/30b2cf/cfd0e6&text=This+image+is+from+dummyimage.com"
                    "posted_at": "2025-03-06T08:00:00Z",
                    "seen": false,
                    "liked": false
                },
                {
                    "id": 1603,
                    "url": "https://www.dummyimage.com/400x600/30b2cf/cfd0e6&text=This+image+is+from+dummyimage.com"
                    "posted_at": "2025-03-06T08:00:00Z",
                    "seen": false,
                    "liked": false
                }
            ]
        },
        {
            "id": 17,
            "user_id": 17,
            "images": [
                {
                    "id": 1700,
                    "url": "https://www.dummyimage.com/400x600/30b2cf/cfd0e6&text=This+image+is+from+dummyimage.com"
                    "posted_at": "2025-03-06T08:00:00Z",
                    "seen": false,
                    "liked": false
                },
                {
                    "id": 1702,
                    "url": "https://www.dummyimage.com/400x600/30b2cf/cfd0e6&text=This+image+is+from+dummyimage.com"
                    "posted_at": "2025-03-06T08:00:00Z",
                    "seen": false,
                    "liked": false
                },
                {
                    "id": 1703,
                    "url": "https://www.dummyimage.com/400x600/30b2cf/cfd0e6&text=This+image+is+from+dummyimage.com"
                    "posted_at": "2025-03-06T08:00:00Z",
                    "seen": false,
                    "liked": false
                }
            ]
        },
        {
            "id": 18,
            "user_id": 18,
            "images": [
                {
                    "id": 1800,
                    "url": "https://www.dummyimage.com/400x600/30b2cf/cfd0e6&text=This+image+is+from+dummyimage.com"
                    "posted_at": "2025-03-06T08:00:00Z",
                    "seen": false,
                    "liked": false
                },
                {
                    "id": 1802,
                    "url": "https://www.dummyimage.com/400x600/30b2cf/cfd0e6&text=This+image+is+from+dummyimage.com"
                    "posted_at": "2025-03-06T08:00:00Z",
                    "seen": false,
                    "liked": false
                },
                {
                    "id": 1803,
                    "url": "https://www.dummyimage.com/400x600/30b2cf/cfd0e6&text=This+image+is+from+dummyimage.com"
                    "posted_at": "2025-03-06T08:00:00Z",
                    "seen": false,
                    "liked": false
                }
            ]
        },
        {
            "id": 19,
            "user_id": 19,
            "images": [
                {
                    "id": 1900,
                    "url": "https://www.dummyimage.com/400x600/30b2cf/cfd0e6&text=This+image+is+from+dummyimage.com"
                    "posted_at": "2025-03-06T08:00:00Z",
                    "seen": false,
                    "liked": false
                },
                {
                    "id": 1902,
                    "url": "https://www.dummyimage.com/400x600/30b2cf/cfd0e6&text=This+image+is+from+dummyimage.com"
                    "posted_at": "2025-03-06T08:00:00Z",
                    "seen": false,
                    "liked": false
                },
                {
                    "id": 1903,
                    "url": "https://www.dummyimage.com/400x600/30b2cf/cfd0e6&text=This+image+is+from+dummyimage.com"
                    "posted_at": "2025-03-06T08:00:00Z",
                    "seen": false,
                    "liked": false
                }
            ]
        },
        {
            "id": 20,
            "user_id": 20,
            "images": [
                {
                    "id": 2000,
                    "url": "https://www.dummyimage.com/400x600/30b2cf/cfd0e6&text=This+image+is+from+dummyimage.com"
                    "posted_at": "2025-03-06T08:00:00Z",
                    "seen": false,
                    "liked": false
                },
                {
                    "id": 2002,
                    "url": "https://www.dummyimage.com/400x600/30b2cf/cfd0e6&text=This+image+is+from+dummyimage.com"
                    "posted_at": "2025-03-06T08:00:00Z",
                    "seen": false,
                    "liked": false
                },
                {
                    "id": 2003,
                    "url": "https://www.dummyimage.com/400x600/30b2cf/cfd0e6&text=This+image+is+from+dummyimage.com"
                    "posted_at": "2025-03-06T08:00:00Z",
                    "seen": false,
                    "liked": false
                }
            ]
        },
        {
            "id": 21,
            "user_id": 21,
            "images": [
                {
                    "id": 2100,
                    "url": "https://www.dummyimage.com/400x600/30b2cf/cfd0e6&text=This+image+is+from+dummyimage.com"
                    "posted_at": "2025-03-06T08:00:00Z",
                    "seen": false,
                    "liked": false
                },
                {
                    "id": 2102,
                    "url": "https://www.dummyimage.com/400x600/30b2cf/cfd0e6&text=This+image+is+from+dummyimage.com"
                    "posted_at": "2025-03-06T08:00:00Z",
                    "seen": false,
                    "liked": false
                },
                {
                    "id": 2103,
                    "url": "https://www.dummyimage.com/400x600/30b2cf/cfd0e6&text=This+image+is+from+dummyimage.com"
                    "posted_at": "2025-03-06T08:00:00Z",
                    "seen": false,
                    "liked": false
                }
            ]
        },
        {
            "id": 22,
            "user_id": 22,
            "images": [
                {
                    "id": 2200,
                    "url": "https://www.dummyimage.com/400x600/30b2cf/cfd0e6&text=This+image+is+from+dummyimage.com"
                    "posted_at": "2025-03-06T08:00:00Z",
                    "seen": false,
                    "liked": false
                },
                {
                    "id": 2202,
                    "url": "https://www.dummyimage.com/400x600/30b2cf/cfd0e6&text=This+image+is+from+dummyimage.com"
                    "posted_at": "2025-03-06T08:00:00Z",
                    "seen": false,
                    "liked": false
                },
                {
                    "id": 2203,
                    "url": "https://www.dummyimage.com/400x600/30b2cf/cfd0e6&text=This+image+is+from+dummyimage.com"
                    "posted_at": "2025-03-06T08:00:00Z",
                    "seen": false,
                    "liked": false
                }
            ]
        },
        {
            "id": 23,
            "user_id": 23,
            "images": [
                {
                    "id": 2300,
                    "url": "https://www.dummyimage.com/400x600/30b2cf/cfd0e6&text=This+image+is+from+dummyimage.com"
                    "posted_at": "2025-03-06T08:00:00Z",
                    "seen": false,
                    "liked": false
                },
                {
                    "id": 2302,
                    "url": "https://www.dummyimage.com/400x600/30b2cf/cfd0e6&text=This+image+is+from+dummyimage.com"
                    "posted_at": "2025-03-06T08:00:00Z",
                    "seen": false,
                    "liked": false
                },
                {
                    "id": 2303,
                    "url": "https://www.dummyimage.com/400x600/30b2cf/cfd0e6&text=This+image+is+from+dummyimage.com"
                    "posted_at": "2025-03-06T08:00:00Z",
                    "seen": false,
                    "liked": false
                }
            ]
        },
        {
            "id": 24,
            "user_id": 24,
            "images": [
                {
                    "id": 2400,
                    "url": "https://www.dummyimage.com/400x600/30b2cf/cfd0e6&text=This+image+is+from+dummyimage.com"
                    "posted_at": "2025-03-06T08:00:00Z",
                    "seen": false,
                    "liked": false
                },
                {
                    "id": 2402,
                    "url": "https://www.dummyimage.com/400x600/30b2cf/cfd0e6&text=This+image+is+from+dummyimage.com"
                    "posted_at": "2025-03-06T08:00:00Z",
                    "seen": false,
                    "liked": false
                },
                {
                    "id": 2403,
                    "url": "https://www.dummyimage.com/400x600/30b2cf/cfd0e6&text=This+image+is+from+dummyimage.com"
                    "posted_at": "2025-03-06T08:00:00Z",
                    "seen": false,
                    "liked": false
                }
            ]
        },
        {
            "id": 25,
            "user_id": 25,
            "images": [
                {
                    "id": 2500,
                    "url": "https://www.dummyimage.com/400x600/30b2cf/cfd0e6&text=This+image+is+from+dummyimage.com"
                    "posted_at": "2025-03-06T08:00:00Z",
                    "seen": false,
                    "liked": false
                },
                {
                    "id": 2502,
                    "url": "https://www.dummyimage.com/400x600/30b2cf/cfd0e6&text=This+image+is+from+dummyimage.com"
                    "posted_at": "2025-03-06T08:00:00Z",
                    "seen": false,
                    "liked": false
                },
                {
                    "id": 2503,
                    "url": "https://www.dummyimage.com/400x600/30b2cf/cfd0e6&text=This+image+is+from+dummyimage.com"
                    "posted_at": "2025-03-06T08:00:00Z",
                    "seen": false,
                    "liked": false
                }
            ]
        },
        {
            "id": 26,
            "user_id": 26,
            "images": [
                {
                    "id": 2600,
                    "url": "https://www.dummyimage.com/400x600/30b2cf/cfd0e6&text=This+image+is+from+dummyimage.com"
                    "posted_at": "2025-03-06T08:00:00Z",
                    "seen": false,
                    "liked": false
                },
                {
                    "id": 2602,
                    "url": "https://www.dummyimage.com/400x600/30b2cf/cfd0e6&text=This+image+is+from+dummyimage.com"
                    "posted_at": "2025-03-06T08:00:00Z",
                    "seen": false,
                    "liked": false
                },
                {
                    "id": 2603,
                    "url": "https://www.dummyimage.com/400x600/30b2cf/cfd0e6&text=This+image+is+from+dummyimage.com"
                    "posted_at": "2025-03-06T08:00:00Z",
                    "seen": false,
                    "liked": false
                }
            ]
        },
        {
            "id": 27,
            "user_id": 27,
            "images": [
                {
                    "id": 2700,
                    "url": "https://www.dummyimage.com/400x600/30b2cf/cfd0e6&text=This+image+is+from+dummyimage.com"
                    "posted_at": "2025-03-06T08:00:00Z",
                    "seen": false,
                    "liked": false
                },
                {
                    "id": 2702,
                    "url": "https://www.dummyimage.com/400x600/30b2cf/cfd0e6&text=This+image+is+from+dummyimage.com"
                    "posted_at": "2025-03-06T08:00:00Z",
                    "seen": false,
                    "liked": false
                },
                {
                    "id": 2703,
                    "url": "https://www.dummyimage.com/400x600/30b2cf/cfd0e6&text=This+image+is+from+dummyimage.com"
                    "posted_at": "2025-03-06T08:00:00Z",
                    "seen": false,
                    "liked": false
                }
            ]
        },
        {
            "id": 28,
            "user_id": 28,
            "images": [
                {
                    "id": 2800,
                    "url": "https://www.dummyimage.com/400x600/30b2cf/cfd0e6&text=This+image+is+from+dummyimage.com"
                    "posted_at": "2025-03-06T08:00:00Z",
                    "seen": false,
                    "liked": false
                },
                {
                    "id": 2802,
                    "url": "https://www.dummyimage.com/400x600/30b2cf/cfd0e6&text=This+image+is+from+dummyimage.com"
                    "posted_at": "2025-03-06T08:00:00Z",
                    "seen": false,
                    "liked": false
                },
                {
                    "id": 2803,
                    "url": "https://www.dummyimage.com/400x600/30b2cf/cfd0e6&text=This+image+is+from+dummyimage.com"
                    "posted_at": "2025-03-06T08:00:00Z",
                    "seen": false,
                    "liked": false
                }
            ]
        },
        {
            "id": 29,
            "user_id": 29,
            "images": [
                {
                    "id": 2900,
                    "url": "https://www.dummyimage.com/400x600/30b2cf/cfd0e6&text=This+image+is+from+dummyimage.com"
                    "posted_at": "2025-03-06T08:00:00Z",
                    "seen": false,
                    "liked": false
                },
                {
                    "id": 2902,
                    "url": "https://www.dummyimage.com/400x600/30b2cf/cfd0e6&text=This+image+is+from+dummyimage.com"
                    "posted_at": "2025-03-06T08:00:00Z",
                    "seen": false,
                    "liked": false
                },
                {
                    "id": 2903,
                    "url": "https://www.dummyimage.com/400x600/30b2cf/cfd0e6&text=This+image+is+from+dummyimage.com"
                    "posted_at": "2025-03-06T08:00:00Z",
                    "seen": false,
                    "liked": false
                }
            ]
        },
        {
            "id": 30,
            "user_id": 30,
            "images": [
                {
                    "id": 3000,
                    "url": "https://www.dummyimage.com/400x600/30b2cf/cfd0e6&text=This+image+is+from+dummyimage.com"
                    "posted_at": "2025-03-06T08:00:00Z",
                    "seen": false,
                    "liked": false
                },
                {
                    "id": 3002,
                    "url": "https://www.dummyimage.com/400x600/30b2cf/cfd0e6&text=This+image+is+from+dummyimage.com"
                    "posted_at": "2025-03-06T08:00:00Z",
                    "seen": false,
                    "liked": false
                },
                {
                    "id": 3003,
                    "url": "https://www.dummyimage.com/400x600/30b2cf/cfd0e6&text=This+image+is+from+dummyimage.com"
                    "posted_at": "2025-03-06T08:00:00Z",
                    "seen": false,
                    "liked": false
                }
            ]
        }
    ]
}
